xospy-0.1.22.dist-info/METADATA
xospy-0.1.22.dist-info/WHEEL
xospy.libs/libasound-dd998a6e.so.2
xospy/__init__.py
xospy/xospy.cpython-311-x86_64-linux-gnu.so
xospy-0.1.22.dist-info/RECORD
