Metadata-Version: 2.4
Name: xospy
Version: 0.1.22
Classifier: Programming Language :: Python :: 3
Classifier: Programming Language :: Rust
Classifier: Operating System :: OS Independent
Requires-Dist: cffi
Summary: Control the XOS operating system from Python.
Author: Dyllan McCreary <dyllan@xlate.ai>
Author-email: Dyllan McCreary <dyllan@xlate.ai>
License: MIT
Requires-Python: >=3.8
